CHANGELOG.md
djangokit/core/__init__.py
djangokit/core/app/client.app.jsx
djangokit/core/app/client.auth.jsx
djangokit/core/app/client.main.jsx
djangokit/core/app/client.wrapper.jsx
djangokit/core/app/context.jsx
djangokit/core/app/routes.jsx
djangokit/core/app/server.app.jsx
djangokit/core/app/server.auth.jsx
djangokit/core/app/server.main.jsx
djangokit/core/app/server.wrapper.jsx
djangokit/core/app/wrapper.jsx
djangokit/core/apps.py
djangokit/core/asgi.py
djangokit/core/build.py
djangokit/core/conf.py
djangokit/core/decorators.py
djangokit/core/exceptions.py
djangokit/core/http.py
djangokit/core/middleware.py
djangokit/core/routes.py
djangokit/core/serializers.py
djangokit/core/settings.py
djangokit/core/static/bootstrap.css
djangokit/core/static/build/client.bundle.js
djangokit/core/static/build/server.bundle.js
djangokit/core/static/global.css
djangokit/core/static.py
djangokit/core/templates/__init__.py
djangokit/core/templates/djangokit/_body.html
djangokit/core/templates/djangokit/_favicon.html
djangokit/core/templates/djangokit/_head.html
djangokit/core/templates/djangokit/_links.html
djangokit/core/templates/djangokit/_meta.html
djangokit/core/templates/djangokit/_scripts.html
djangokit/core/templates/djangokit/_stylesheets.html
djangokit/core/templates/djangokit/_title.html
djangokit/core/templates/djangokit/app.html
djangokit/core/templates/djangokit/base/_body.html
djangokit/core/templates/djangokit/base/_favicon.html
djangokit/core/templates/djangokit/base/_head.html
djangokit/core/templates/djangokit/base/_links.html
djangokit/core/templates/djangokit/base/_meta.html
djangokit/core/templates/djangokit/base/_scripts.html
djangokit/core/templates/djangokit/base/_stylesheets.html
djangokit/core/templates/djangokit/base/_title.html
djangokit/core/templates/djangokit/base.html
djangokit/core/templates/djangokit/error.html
djangokit/core/templates/loader.py
djangokit/core/test/__init__.py
djangokit/core/test/apps.py
djangokit/core/test/models/__init__.py
org_djangokit_core-0.0.4.dist-info/LICENSE
org_djangokit_core-0.0.4.dist-info/WHEEL
org_djangokit_core-0.0.4.dist-info/METADATA
org_djangokit_core-0.0.4.dist-info/RECORD
